CHANGELOG.rst
CONTRIBUTORS.rst
LICENSE
MANIFEST.in
README.rst
setup.py
vcs-mirrors.yaml.sample
vcs_mirrors/__init__.py
vcs_mirrors.egg-info/PKG-INFO
vcs_mirrors.egg-info/SOURCES.txt
vcs_mirrors.egg-info/dependency_links.txt
vcs_mirrors.egg-info/entry_points.txt
vcs_mirrors.egg-info/not-zip-safe
vcs_mirrors.egg-info/requires.txt
vcs_mirrors.egg-info/top_level.txt
vcs_mirrors/command/add.py
vcs_mirrors/command/sync.py
vcs_mirrors/command/sync_all.py
vcs_mirrors/host/__init__.py
vcs_mirrors/host/github.py
vcs_mirrors/host/gitlab.py
vcs_mirrors/lib/__init__.py
vcs_mirrors/lib/cd.py
vcs_mirrors/lib/config.py
vcs_mirrors/lib/interfaces.py
vcs_mirrors/lib/loader.py
vcs_mirrors/lib/utils.py
vcs_mirrors/repo/__init__.py
vcs_mirrors/repo/bazaar.py
vcs_mirrors/repo/git.py
vcs_mirrors/scripts/__init__.py
vcs_mirrors/scripts/main.py