Metadata-Version: 2.1
Name: vcs-mirrors
Version: 0.0.7
Summary: UNKNOWN
Home-page: https://git.lxch.eu/pcdummy/vcs-mirrors
Author: René Jochum
Author-email: rene@jochums.at
License: MIT
Keywords: Console VCS mirror vcs-mirrors
Platform: UNKNOWN
Classifier: Programming Language :: Python
Classifier: Programming Language :: Python :: 3
Classifier: Programming Language :: Python :: 3.5
Classifier: Programming Language :: Python :: 3.6
Classifier: License :: OSI Approved :: MIT License
Classifier: Topic :: Software Development :: Version Control
Classifier: Topic :: Software Development :: Version Control :: Bazaar
Classifier: Topic :: Software Development :: Version Control :: Git
Provides-Extra: gitlab
Provides-Extra: development
Provides-Extra: github
